CHANGELOG.txt
LICENCE.txt
MANIFEST.in
README.txt
setup.py
E13Testing1.egg-info/PKG-INFO
E13Testing1.egg-info/SOURCES.txt
E13Testing1.egg-info/dependency_links.txt
E13Testing1.egg-info/top_level.txt
Testing/__init__.py