Metadata-Version: 2.1
Name: E13Testing1
Version: 0.0.1
Summary: A very basic calculator
Home-page: 
Author: E13_
Author-email: E13OnTop@gmail.com
License: MIT
Keywords: test
Classifier: Development Status :: 5 - Production/Stable
Classifier: Intended Audience :: Education
Classifier: Operating System :: Microsoft :: Windows :: Windows 10
Classifier: License :: OSI Approved :: MIT License
Classifier: Programming Language :: Python :: 3
License-File: LICENCE.txt
